{
  "description_properties": ["1.16.100"],
  "description_is_experimental": ["1.12.0", "1.16.0"],
  "description_register_to_creative_menu": ["1.12.0", "1.16.0"],
  "components_display_name": ["1.16.100"],
  "components_tag": ["1.16.100"],
  "components_placement_filter": ["1.16.100"],
  "components_preventsjumping": ["1.16.100"],
  "components_unwalkable": ["1.16.100"],
  "components_crafting_table": ["1.16.100"],
  "components_unit_cube": ["1.16.100"],
  "components_geometry": ["1.16.100"],
  "components_material_instances": ["1.16.100"],
  "components_entity_collision": ["1.16.100"],
  "components_pick_collision": ["1.16.100"],
  "components_rotation": ["1.16.100"],
  "components_breathability": ["1.16.100"],
  "components_breakonpush": ["1.16.100"],
  "components_immovable": ["1.16.100"],
  "components_onlypistonpush": ["1.16.100"],
  "components_event_on_fall_on": ["1.16.100"],
  "components_event_on_interact": ["1.16.100"],
  "components_event_on_placed": ["1.16.100"],
  "components_event_on_player_placing": ["1.16.100"],
  "components_event_on_step_on": ["1.16.100"],
  "components_event_on_step_off": ["1.16.100"],
  "components_event_on_player_destroyed": ["1.16.100"],
  "components_event_ticking": ["1.16.100"],
  "components_event_random_ticking": ["1.16.100"],
  "event_responses_set_block_property": ["1.16.100"],
  "event_responses_set_block_at_pos": ["1.16.100"],
  "event_responses_spawn_loot": ["1.16.100"],
  "event_responses_add_mob_effect": ["1.16.100"],
  "event_responses_remove_mob_effect": ["1.16.100"],
  "event_responses_damage": ["1.16.100"],
  "event_responses_decrement_stack": ["1.16.100"],
  "event_responses_die": ["1.16.100"],
  "event_responses_play_effect": ["1.16.100"],
  "event_responses_play_sound": ["1.16.100"],
  "event_responses_teleport": ["1.16.100"],
  "event_responses_transform_item": ["1.16.100"],
  "event_responses_trigger": ["1.16.100"],
  "event_responses_run_command": ["1.16.100"],
  "event_responses_swing": ["1.16.100"],
  "event_responses_sequence": ["1.16.100"],
  "event_responses_randomize": ["1.16.100"]
}
